tipg/__init__.py
tipg/collections.py
tipg/database.py
tipg/dependencies.py
tipg/errors.py
tipg/factory.py
tipg/logger.py
tipg/main.py
tipg/middleware.py
tipg/model.py
tipg/openapi.py
tipg/py.typed
tipg/settings.py
tipg/filter/__init__.py
tipg/filter/evaluate.py
tipg/filter/filters.py
tipg/resources/__init__.py
tipg/resources/enums.py
tipg/resources/response.py
tipg/sql/dbcatalog.sql
tipg/templates/collection.html
tipg/templates/collections.html
tipg/templates/conformance.html
tipg/templates/debug.html
tipg/templates/footer.html
tipg/templates/header.html
tipg/templates/item.html
tipg/templates/items.html
tipg/templates/landing.html
tipg/templates/map.html
tipg/templates/queryables.html
tipg/templates/tilematrixset.html
tipg/templates/tilematrixsets.html
tipg/templates/tileset.html
tipg/templates/tilesets.html
tipg-1.2.1.dist-info/METADATA
tipg-1.2.1.dist-info/WHEEL
tipg-1.2.1.dist-info/licenses/LICENSE
tipg-1.2.1.dist-info/RECORD
