Metadata-Version: 2.4
Name: tipg
Version: 1.2.1
Summary: Simple and Fast Geospatial OGC Features and Tiles API for PostGIS.
Project-URL: Homepage, https://developmentseed.org/tipg
Project-URL: Source, https://github.com/developmentseed/tipg
Project-URL: Documentation, https://developmentseed.org/tipg/
Author-email: Vincent Sarago <vincent@developmentseed.org>, David Bitner <david@developmentseed.org>
License: MIT License
License-File: LICENSE
Keywords: FastAPI,OGC Features,OGC Tiles,POSTGIS
Classifier: Intended Audience :: Information Technology
Classifier: Intended Audience :: Science/Research
Classifier: License :: OSI Approved :: BSD License
Classifier: Programming Language :: Python :: 3.9
Classifier: Programming Language :: Python :: 3.10
Classifier: Programming Language :: Python :: 3.11
Classifier: Programming Language :: Python :: 3.12
Classifier: Programming Language :: Python :: 3.13
Classifier: Topic :: Scientific/Engineering :: GIS
Requires-Python: >=3.9
Requires-Dist: asyncpg>=0.23.0
Requires-Dist: buildpg>=0.3
Requires-Dist: ciso8601~=2.3
Requires-Dist: fastapi>=0.100.0
Requires-Dist: geojson-pydantic<3.0,>=1.0
Requires-Dist: jinja2<4.0.0,>=2.11.2
Requires-Dist: morecantile<7.0,>=5.0
Requires-Dist: orjson
Requires-Dist: pydantic-settings~=2.0
Requires-Dist: pydantic<3.0,>=2.4
Requires-Dist: pygeofilter<0.3.0,>=0.2.0
Requires-Dist: starlette-cramjam<0.6,>=0.4
Provides-Extra: dev
Requires-Dist: bump-my-version; extra == 'dev'
Requires-Dist: pre-commit; extra == 'dev'
Provides-Extra: docs
Requires-Dist: black>=23.10.1; extra == 'docs'
Requires-Dist: griffe-inherited-docstrings>=1.0.0; extra == 'docs'
Requires-Dist: mkdocs; extra == 'docs'
Requires-Dist: mkdocs-material[imaging]>=9.5; extra == 'docs'
Requires-Dist: mkdocstrings[python]>=0.25.1; extra == 'docs'
Provides-Extra: server
Requires-Dist: uvicorn[standard]<0.19.0,>=0.12.0; extra == 'server'
Provides-Extra: test
Requires-Dist: httpx; extra == 'test'
Requires-Dist: mapbox-vector-tile>=2.1; extra == 'test'
Requires-Dist: numpy; extra == 'test'
Requires-Dist: pytest; extra == 'test'
Requires-Dist: pytest-asyncio; extra == 'test'
Requires-Dist: pytest-benchmark; extra == 'test'
Requires-Dist: pytest-cov; extra == 'test'
Requires-Dist: pytest-postgresql; extra == 'test'
